ndmap/__init__.py
ndmap/bracket.py
ndmap/complex.py
ndmap/derivative.py
ndmap/evaluate.py
ndmap/expression.py
ndmap/factorization.py
ndmap/gradient.py
ndmap/index.py
ndmap/invariant.py
ndmap/inverse.py
ndmap/jet.py
ndmap/matrix.py
ndmap/momenta.py
ndmap/pfp.py
ndmap/propagate.py
ndmap/series.py
ndmap/signature.py
ndmap/symplectify.py
ndmap/taylor.py
ndmap/util.py
ndmap/yoshida.py
ndmap-0.1.7.dist-info/LICENSE
ndmap-0.1.7.dist-info/METADATA
ndmap-0.1.7.dist-info/WHEEL
ndmap-0.1.7.dist-info/top_level.txt
ndmap-0.1.7.dist-info/RECORD
