Metadata-Version: 2.1
Name: ndmap
Version: 0.1.7
Summary: Higher order partial derivatives computation with respect to one or several tensor-like variables, application to nonlinear dynamics
Author: Ivan Morozov
License: MIT
Keywords: torch,derivative
Classifier: Programming Language :: Python :: 3
Requires-Python: >=3.10
License-File: LICENSE
Requires-Dist: torch >=2.0.1
Requires-Dist: multimethod >=1.9.1
Requires-Dist: numpy >=1.23.5
Provides-Extra: all
Requires-Dist: ndtorch[examples,test] ; extra == 'all'
Provides-Extra: examples
Requires-Dist: jupyter-lab ; extra == 'examples'
Requires-Dist: matplotlib ; extra == 'examples'
Requires-Dist: twiss ; extra == 'examples'
Provides-Extra: test
Requires-Dist: pytest ; extra == 'test'
Requires-Dist: pytest-cov ; extra == 'test'
Requires-Dist: pylint ; extra == 'test'
Requires-Dist: mypy ; extra == 'test'
